{"connect":{"statusCode":200,"response":{"id":"","name":"TimeX","private":false,"enableRateLimit":true,"countries":["AU"],"rateLimit":1500,"has":{"loadMarkets":"true","cancelAllOrders":"false","cancelOrder":"true","cancelOrders":"true","CORS":"false","createDepositAddress":"false","createLimitOrder":"true","createMarketOrder":"true","createOrder":"true","deposit":"false","editOrder":"true","fetchBalance":"true","fetchBidsAsks":"false","fetchClosedOrders":"true","fetchCurrencies":"true","fetchDepositAddress":"false","fetchDeposits":"false","fetchFundingFees":"false","fetchL2OrderBook":"true","fetchLedger":"false","fetchMarkets":"true","fetchMyTrades":"true","fetchOHLCV":"true","fetchOpenOrders":"true","fetchOrder":"true","fetchOrderBook":"true","fetchOrderBooks":"false","fetchOrders":"false","fetchOrderTrades":"false","fetchStatus":"emulated","fetchTicker":"true","fetchTickers":"true","fetchTime":"false","fetchTrades":"true","fetchTradingFee":"true","fetchTradingFees":"false","fetchTradingLimits":"false","fetchTransactions":"false","fetchWithdrawals":"false","privateAPI":"true","publicAPI":"true","withdraw":"false"},"urls":{"logo":"https://user-images.githubusercontent.com/1294454/70423869-6839ab00-1a7f-11ea-8f94-13ae72c31115.jpg","api":"https://plasma-relay-backend.timex.io","www":"https://timex.io","doc":"https://docs.timex.io","referral":"https://timex.io/?refcode=1x27vNkTbP1uwkCck"}}},"markets":{"statusCode":200,"response":[{"id":"TPTBTC","symbol":"TPT/BTC","base":"TPT","quote":"BTC","info":{"symbol":"TPTBTC","name":"TPT/BTC","baseCurrency":"TPT","baseTokenAddress":"0x5a07cde9c49c348de727a8ebafdb8851c4e9b5e3","quoteCurrency":"BTC","quoteTokenAddress":"0x8370fbc6ddec1e18b4e41e72ed943e238458487c","feeCurrency":"BTC","feeTokenAddress":"0x8370fbc6ddec1e18b4e41e72ed943e238458487c","alternativeCurrency":null,"alternativeTokenAddress":null,"quantityIncrement":"1","takerFee":"0.005","makerFee":"0.0025","takerAltFee":null,"makerAltFee":null,"tickSize":"0.00001","baseMinSize":"1","quoteMinSize":"0.00001","locked":true,"promotional":false,"showOnLanding":false,"sortOrder":31},"limits":{"amount":{"min":1},"price":{"min":0.00001},"cost":{"min":0.00001}},"precision":{"amount":0,"price":5}},{"id":"BTCAUDT","symbol":"BTC/AUDT","base":"BTC","quote":"AUDT","info":{"symbol":"BTCAUDT","name":"BTC/AUDT","baseCurrency":"BTC","baseTokenAddress":"0x8370fbc6ddec1e18b4e41e72ed943e238458487c","quoteCurrency":"AUDT","quoteTokenAddress":"0xd7e0f80fb28233bdde0006c50568606a8feb964c","feeCurrency":"AUDT","feeTokenAddress":"0xd7e0f80fb28233bdde0006c50568606a8feb964c","alternativeCurrency":null,"alternativeTokenAddress":null,"quantityIncrement":"0.001","takerFee":"0.005","makerFee":"0.0025","takerAltFee":null,"makerAltFee":null,"tickSize":"0.01","baseMinSize":"0.005","quoteMinSize":"30","locked":false,"promotional":false,"showOnLanding":true,"sortOrder":1},"limits":{"amount":{"min":0.005},"price":{"min":0.01},"cost":{"min":30}},"precision":{"amount":3,"price":2}},{"id":"TIMEETH","symbol":"TIME/ETH","base":"TIME","quote":"ETH","info":{"symbol":"TIMEETH","name":"TIME/ETH","baseCurrency":"TIME","baseTokenAddress":"0x6531f133e6deebe7f2dce5a0441aa7ef330b4e53","quoteCurrency":"ETH","quoteTokenAddress":"0x45932db54b38af1f5a57136302eeba66a5975c15","feeCurrency":"ETH","feeTokenAddress":"0x45932db54b38af1f5a57136302eeba66a5975c15","alternativeCurrency":null,"alternativeTokenAddress":null,"quantityIncrement":"0.000001","takerFee":"0.005","makerFee":"0.0025","takerAltFee":null,"makerAltFee":null,"tickSize":"0.0000001","baseMinSize":"0.01","quoteMinSize":"0.0001","locked":false,"promotional":true,"showOnLanding":false,"sortOrder":23},"limits":{"amount":{"min":0.01},"price":{"min":1e-7},"cost":{"min":0.0001}},"precision":{"amount":6,"price":7}},{"id":"ETHBTC","symbol":"ETH/BTC","base":"ETH","quote":"BTC","info":{"symbol":"ETHBTC","name":"ETH/BTC","baseCurrency":"ETH","baseTokenAddress":"0x45932db54b38af1f5a57136302eeba66a5975c15","quoteCurrency":"BTC","quoteTokenAddress":"0x8370fbc6ddec1e18b4e41e72ed943e238458487c","feeCurrency":"BTC","feeTokenAddress":"0x8370fbc6ddec1e18b4e41e72ed943e238458487c","alternativeCurrency":null,"alternativeTokenAddress":null,"quantityIncrement":"0.001","takerFee":"0.005","makerFee":"0.0025","takerAltFee":null,"makerAltFee":null,"tickSize":"0.000001","baseMinSize":"0.001","quoteMinSize":"0.0001","locked":false,"promotional":true,"showOnLanding":false,"sortOrder":25},"limits":{"amount":{"min":0.001},"price":{"min":0.000001},"cost":{"min":0.0001}},"precision":{"amount":3,"price":6}},{"id":"ETHAUDT","symbol":"ETH/AUDT","base":"ETH","quote":"AUDT","info":{"symbol":"ETHAUDT","name":"ETH/AUDT","baseCurrency":"ETH","baseTokenAddress":"0x45932db54b38af1f5a57136302eeba66a5975c15","quoteCurrency":"AUDT","quoteTokenAddress":"0xd7e0f80fb28233bdde0006c50568606a8feb964c","feeCurrency":"AUDT","feeTokenAddress":"0xd7e0f80fb28233bdde0006c50568606a8feb964c","alternativeCurrency":null,"alternativeTokenAddress":null,"quantityIncrement":"0.001","takerFee":"0.005","makerFee":"0.0025","takerAltFee":null,"makerAltFee":null,"tickSize":"0.01","baseMinSize":"0.2","quoteMinSize":"30","locked":false,"promotional":false,"showOnLanding":true,"sortOrder":2},"limits":{"amount":{"min":0.2},"price":{"min":0.01},"cost":{"min":30}},"precision":{"amount":3,"price":2}},{"id":"LTCAUDT","symbol":"LTC/AUDT","base":"LTC","quote":"AUDT","info":{"symbol":"LTCAUDT","name":"LTC/AUDT","baseCurrency":"LTC","baseTokenAddress":"0x2a5cf1cf897c14513d880491c39d402fb9385fc7","quoteCurrency":"AUDT","quoteTokenAddress":"0xd7e0f80fb28233bdde0006c50568606a8feb964c","feeCurrency":"AUDT","feeTokenAddress":"0xd7e0f80fb28233bdde0006c50568606a8feb964c","alternativeCurrency":null,"alternativeTokenAddress":null,"quantityIncrement":"0.1","takerFee":"0.005","makerFee":"0.0025","takerAltFee":null,"makerAltFee":null,"tickSize":"0.001","baseMinSize":"0.1","quoteMinSize":"30","locked":false,"promotional":false,"showOnLanding":false,"sortOrder":4},"limits":{"amount":{"min":0.1},"price":{"min":0.001},"cost":{"min":30}},"precision":{"amount":1,"price":3}},{"id":"USDTAUDT","symbol":"USDT/AUDT","base":"USDT","quote":"AUDT","info":{"symbol":"USDTAUDT","name":"USDT/AUDT","baseCurrency":"USDT","baseTokenAddress":"0xdac17f958d2ee523a2206206994597c13d831ec7","quoteCurrency":"AUDT","quoteTokenAddress":"0xd7e0f80fb28233bdde0006c50568606a8feb964c","feeCurrency":"AUDT","feeTokenAddress":"0xd7e0f80fb28233bdde0006c50568606a8feb964c","alternativeCurrency":null,"alternativeTokenAddress":null,"quantityIncrement":"0.01","takerFee":"0.005","makerFee":"0.0025","takerAltFee":null,"makerAltFee":null,"tickSize":"0.0001","baseMinSize":"0.01","quoteMinSize":"10","locked":false,"promotional":false,"showOnLanding":false,"sortOrder":5},"limits":{"amount":{"min":0.01},"price":{"min":0.0001},"cost":{"min":10}},"precision":{"amount":2,"price":4}},{"id":"BTCUSDT","symbol":"BTC/USDT","base":"BTC","quote":"USDT","info":{"symbol":"BTCUSDT","name":"BTC/USDT","baseCurrency":"BTC","baseTokenAddress":"0x8370fbc6ddec1e18b4e41e72ed943e238458487c","quoteCurrency":"USDT","quoteTokenAddress":"0xdac17f958d2ee523a2206206994597c13d831ec7","feeCurrency":"USDT","feeTokenAddress":"0xdac17f958d2ee523a2206206994597c13d831ec7","alternativeCurrency":null,"alternativeTokenAddress":null,"quantityIncrement":"0.000001","takerFee":"0.005","makerFee":"0.0025","takerAltFee":null,"makerAltFee":null,"tickSize":"0.01","baseMinSize":"0.00001","quoteMinSize":"1","locked":false,"promotional":false,"showOnLanding":true,"sortOrder":6},"limits":{"amount":{"min":0.00001},"price":{"min":0.01},"cost":{"min":1}},"precision":{"amount":6,"price":2}},{"id":"ETHUSDT","symbol":"ETH/USDT","base":"ETH","quote":"USDT","info":{"symbol":"ETHUSDT","name":"ETH/USDT","baseCurrency":"ETH","baseTokenAddress":"0x45932db54b38af1f5a57136302eeba66a5975c15","quoteCurrency":"USDT","quoteTokenAddress":"0xdac17f958d2ee523a2206206994597c13d831ec7","feeCurrency":"USDT","feeTokenAddress":"0xdac17f958d2ee523a2206206994597c13d831ec7","alternativeCurrency":null,"alternativeTokenAddress":null,"quantityIncrement":"0.0001","takerFee":"0.005","makerFee":"0.0025","takerAltFee":null,"makerAltFee":null,"tickSize":"0.001","baseMinSize":"0.00001","quoteMinSize":"0.00001","locked":false,"promotional":false,"showOnLanding":true,"sortOrder":7},"limits":{"amount":{"min":0.0001},"price":{"min":0.001},"cost":{"min":0.00001}},"precision":{"amount":4,"price":3}},{"id":"TIMEBTC","symbol":"TIME/BTC","base":"TIME","quote":"BTC","info":{"symbol":"TIMEBTC","name":"TIME/BTC","baseCurrency":"TIME","baseTokenAddress":"0x6531f133e6deebe7f2dce5a0441aa7ef330b4e53","quoteCurrency":"BTC","quoteTokenAddress":"0x8370fbc6ddec1e18b4e41e72ed943e238458487c","feeCurrency":"BTC","feeTokenAddress":"0x8370fbc6ddec1e18b4e41e72ed943e238458487c","alternativeCurrency":null,"alternativeTokenAddress":null,"quantityIncrement":"0.000001","takerFee":"0.005","makerFee":"0.0025","takerAltFee":null,"makerAltFee":null,"tickSize":"0.00000001","baseMinSize":"0.01","quoteMinSize":"0.00001","locked":false,"promotional":true,"showOnLanding":false,"sortOrder":10},"limits":{"amount":{"min":0.01},"price":{"min":1e-8},"cost":{"min":0.00001}},"precision":{"amount":6,"price":8}},{"id":"XRPUSDT","symbol":"XRP/USDT","base":"XRP","quote":"USDT","info":{"symbol":"XRPUSDT","name":"XRP/USDT","baseCurrency":"XRP","baseTokenAddress":"0x0dc8882914f3ddeebf4cec6dc20edb99df3def6c","quoteCurrency":"USDT","quoteTokenAddress":"0xdac17f958d2ee523a2206206994597c13d831ec7","feeCurrency":"USDT","feeTokenAddress":"0xdac17f958d2ee523a2206206994597c13d831ec7","alternativeCurrency":null,"alternativeTokenAddress":null,"quantityIncrement":"100","takerFee":"0.005","makerFee":"0.0025","takerAltFee":null,"makerAltFee":null,"tickSize":"0.00001","baseMinSize":"100","quoteMinSize":"30","locked":false,"promotional":false,"showOnLanding":true,"sortOrder":8},"limits":{"amount":{"min":100},"price":{"min":0.00001},"cost":{"min":30}},"precision":{"amount":0,"price":5}},{"id":"LTCUSDT","symbol":"LTC/USDT","base":"LTC","quote":"USDT","info":{"symbol":"LTCUSDT","name":"LTC/USDT","baseCurrency":"LTC","baseTokenAddress":"0x2a5cf1cf897c14513d880491c39d402fb9385fc7","quoteCurrency":"USDT","quoteTokenAddress":"0xdac17f958d2ee523a2206206994597c13d831ec7","feeCurrency":"USDT","feeTokenAddress":"0xdac17f958d2ee523a2206206994597c13d831ec7","alternativeCurrency":null,"alternativeTokenAddress":null,"quantityIncrement":"0.1","takerFee":"0.005","makerFee":"0.0025","takerAltFee":null,"makerAltFee":null,"tickSize":"0.001","baseMinSize":"0.1","quoteMinSize":"30","locked":false,"promotional":false,"showOnLanding":true,"sortOrder":9},"limits":{"amount":{"min":0.1},"price":{"min":0.001},"cost":{"min":30}},"precision":{"amount":1,"price":3}},{"id":"XRPAUDT","symbol":"XRP/AUDT","base":"XRP","quote":"AUDT","info":{"symbol":"XRPAUDT","name":"XRP/AUDT","baseCurrency":"XRP","baseTokenAddress":"0x0dc8882914f3ddeebf4cec6dc20edb99df3def6c","quoteCurrency":"AUDT","quoteTokenAddress":"0xd7e0f80fb28233bdde0006c50568606a8feb964c","feeCurrency":"AUDT","feeTokenAddress":"0xd7e0f80fb28233bdde0006c50568606a8feb964c","alternativeCurrency":null,"alternativeTokenAddress":null,"quantityIncrement":"100","takerFee":"0.005","makerFee":"0.0025","takerAltFee":null,"makerAltFee":null,"tickSize":"0.00001","baseMinSize":"100","quoteMinSize":"30","locked":false,"promotional":false,"showOnLanding":true,"sortOrder":3},"limits":{"amount":{"min":100},"price":{"min":0.00001},"cost":{"min":30}},"precision":{"amount":0,"price":5}},{"id":"TPTAUDT","symbol":"TPT/AUDT","base":"TPT","quote":"AUDT","info":{"symbol":"TPTAUDT","name":"TPT/AUDT","baseCurrency":"TPT","baseTokenAddress":"0x5a07cde9c49c348de727a8ebafdb8851c4e9b5e3","quoteCurrency":"AUDT","quoteTokenAddress":"0xd7e0f80fb28233bdde0006c50568606a8feb964c","feeCurrency":"AUDT","feeTokenAddress":"0xd7e0f80fb28233bdde0006c50568606a8feb964c","alternativeCurrency":null,"alternativeTokenAddress":null,"quantityIncrement":"1","takerFee":"0.005","makerFee":"0.0025","takerAltFee":null,"makerAltFee":null,"tickSize":"0.01","baseMinSize":"1","quoteMinSize":"5","locked":true,"promotional":false,"showOnLanding":false,"sortOrder":29},"limits":{"amount":{"min":1},"price":{"min":0.01},"cost":{"min":5}},"precision":{"amount":0,"price":2}},{"id":"TPTUSDT","symbol":"TPT/USDT","base":"TPT","quote":"USDT","info":{"symbol":"TPTUSDT","name":"TPT/USDT","baseCurrency":"TPT","baseTokenAddress":"0x5a07cde9c49c348de727a8ebafdb8851c4e9b5e3","quoteCurrency":"USDT","quoteTokenAddress":"0xdac17f958d2ee523a2206206994597c13d831ec7","feeCurrency":"USDT","feeTokenAddress":"0xdac17f958d2ee523a2206206994597c13d831ec7","alternativeCurrency":null,"alternativeTokenAddress":null,"quantityIncrement":"1","takerFee":"0.005","makerFee":"0.0025","takerAltFee":null,"makerAltFee":null,"tickSize":"0.01","baseMinSize":"1","quoteMinSize":"3","locked":true,"promotional":false,"showOnLanding":false,"sortOrder":30},"limits":{"amount":{"min":1},"price":{"min":0.01},"cost":{"min":3}},"precision":{"amount":0,"price":2}}]},"ticker":{"statusCode":200,"response":{"symbol":"TPT/BTC","timestamp":1592834169092,"datetime":"2020-06-22T13:56:09.092Z","close":0.0005,"last":0.0005,"baseVolume":0,"quoteVolume":0,"info":{"market":"TPTBTC","period":"D1","timestamp":"2020-06-22T13:56:09.092Z","ask":null,"bid":null,"open":"0.0005","high":null,"low":null,"last":"0.0005","volume":"0","volumeQuote":"0"}}},"tickers":{"statusCode":200,"response":[{"symbol":"BTC/AUDT","timestamp":1592834170611,"datetime":"2020-06-22T13:56:10.611Z","bid":13721.23,"ask":13733.85,"close":13728.8,"last":13728.8,"baseVolume":56.691,"quoteVolume":775907.06587,"info":{"market":"BTCAUDT","period":"D1","timestamp":"2020-06-22T13:56:10.611Z","ask":"13733.85","bid":"13721.23","open":"13709.96","high":null,"low":null,"last":"13728.8","volume":"56.691","volumeQuote":"775907.06587"}},{"symbol":"BTC/USDT","timestamp":1592834170612,"datetime":"2020-06-22T13:56:10.612Z","bid":9453.61,"ask":9493.2,"close":9469.69,"last":9469.69,"baseVolume":25.210963,"quoteVolume":236326.20463544,"info":{"market":"BTCUSDT","period":"D1","timestamp":"2020-06-22T13:56:10.612Z","ask":"9493.2","bid":"9453.61","open":"9338.04","high":null,"low":null,"last":"9469.69","volume":"25.210963","volumeQuote":"236326.20463544"}},{"symbol":"ETH/AUDT","timestamp":1592834170611,"datetime":"2020-06-22T13:56:10.611Z","bid":345.55,"ask":345.92,"close":346.15,"last":346.15,"baseVolume":6373.115,"quoteVolume":2150542.21955,"info":{"market":"ETHAUDT","period":"D1","timestamp":"2020-06-22T13:56:10.611Z","ask":"345.92","bid":"345.55","open":"337.46","high":null,"low":null,"last":"346.15","volume":"6373.115","volumeQuote":"2150542.21955"}},{"symbol":"ETH/BTC","timestamp":1592834170611,"datetime":"2020-06-22T13:56:10.611Z","bid":0.025123,"ask":0.025128,"close":0.02513,"last":0.02513,"baseVolume":554.219,"quoteVolume":13.71482376,"info":{"market":"ETHBTC","period":"D1","timestamp":"2020-06-22T13:56:10.611Z","ask":"0.025128","bid":"0.025123","open":"0.024567","high":null,"low":null,"last":"0.02513","volume":"554.219","volumeQuote":"13.71482376"}},{"symbol":"ETH/USDT","timestamp":1592834170612,"datetime":"2020-06-22T13:56:10.612Z","bid":237.705,"ask":238.362,"close":237.848,"last":237.848,"baseVolume":1664.1851,"quoteVolume":383855.9905155,"info":{"market":"ETHUSDT","period":"D1","timestamp":"2020-06-22T13:56:10.612Z","ask":"238.362","bid":"237.705","open":"229.375","high":null,"low":null,"last":"237.848","volume":"1664.1851","volumeQuote":"383855.9905155"}},{"symbol":"LTC/AUDT","timestamp":1592834170611,"datetime":"2020-06-22T13:56:10.611Z","bid":63.352,"ask":63.604,"close":63.51,"last":63.51,"baseVolume":1438.7,"quoteVolume":91052.7191,"info":{"market":"LTCAUDT","period":"D1","timestamp":"2020-06-22T13:56:10.611Z","ask":"63.604","bid":"63.352","open":"63.266","high":null,"low":null,"last":"63.51","volume":"1438.7","volumeQuote":"91052.7191"}},{"symbol":"LTC/USDT","timestamp":1592834170612,"datetime":"2020-06-22T13:56:10.612Z","bid":43.836,"ask":43.846,"close":43.84,"last":43.84,"baseVolume":1192,"quoteVolume":51664.4549,"info":{"market":"LTCUSDT","period":"D1","timestamp":"2020-06-22T13:56:10.612Z","ask":"43.846","bid":"43.836","open":"43.176","high":null,"low":null,"last":"43.84","volume":"1192","volumeQuote":"51664.4549"}},{"symbol":"TIME/BTC","timestamp":1592834170612,"datetime":"2020-06-22T13:56:10.612Z","bid":0.00025961,"ask":0.00026443,"close":0.00026151,"last":0.00026151,"baseVolume":6104.980727,"quoteVolume":1.50130934631544,"info":{"market":"TIMEBTC","period":"D1","timestamp":"2020-06-22T13:56:10.612Z","ask":"0.00026443","bid":"0.00025961","open":"0.00021689","high":null,"low":null,"last":"0.00026151","volume":"6104.980727","volumeQuote":"1.50130934631544"}},{"symbol":"TIME/ETH","timestamp":1592834170611,"datetime":"2020-06-22T13:56:10.611Z","bid":0.0080485,"ask":0.0081967,"close":0.0080481,"last":0.0080481,"baseVolume":326.112053,"quoteVolume":2.6096839501462,"info":{"market":"TIMEETH","period":"D1","timestamp":"2020-06-22T13:56:10.611Z","ask":"0.0081967","bid":"0.0080485","open":"0.0080598","high":null,"low":null,"last":"0.0080481","volume":"326.112053","volumeQuote":"2.6096839501462"}},{"symbol":"TPT/AUDT","timestamp":1592834170612,"datetime":"2020-06-22T13:56:10.612Z","close":5.01,"last":5.01,"baseVolume":0,"quoteVolume":0,"info":{"market":"TPTAUDT","period":"D1","timestamp":"2020-06-22T13:56:10.612Z","ask":null,"bid":null,"open":"5.01","high":null,"low":null,"last":"5.01","volume":"0","volumeQuote":"0"}},{"symbol":"TPT/BTC","timestamp":1592834170611,"datetime":"2020-06-22T13:56:10.611Z","close":0.0005,"last":0.0005,"baseVolume":0,"quoteVolume":0,"info":{"market":"TPTBTC","period":"D1","timestamp":"2020-06-22T13:56:10.611Z","ask":null,"bid":null,"open":"0.0005","high":null,"low":null,"last":"0.0005","volume":"0","volumeQuote":"0"}},{"symbol":"TPT/USDT","timestamp":1592834170612,"datetime":"2020-06-22T13:56:10.612Z","close":3.03,"last":3.03,"baseVolume":0,"quoteVolume":0,"info":{"market":"TPTUSDT","period":"D1","timestamp":"2020-06-22T13:56:10.612Z","ask":null,"bid":null,"open":"3.03","high":null,"low":null,"last":"3.03","volume":"0","volumeQuote":"0"}},{"symbol":"USDT/AUDT","timestamp":1592834170612,"datetime":"2020-06-22T13:56:10.612Z","bid":1.4544,"ask":1.4548,"close":1.4547,"last":1.4547,"baseVolume":10912.69,"quoteVolume":15963.498004,"info":{"market":"USDTAUDT","period":"D1","timestamp":"2020-06-22T13:56:10.612Z","ask":"1.4548","bid":"1.4544","open":"1.4635","high":null,"low":null,"last":"1.4547","volume":"10912.69","volumeQuote":"15963.498004"}},{"symbol":"XRP/AUDT","timestamp":1592834170612,"datetime":"2020-06-22T13:56:10.612Z","bid":0.27271,"ask":0.27275,"close":0.27273,"last":0.27273,"baseVolume":214200,"quoteVolume":58875.844,"info":{"market":"XRPAUDT","period":"D1","timestamp":"2020-06-22T13:56:10.612Z","ask":"0.27275","bid":"0.27271","open":"0.27474","high":null,"low":null,"last":"0.27273","volume":"214200","volumeQuote":"58875.844"}},{"symbol":"XRP/USDT","timestamp":1592834170612,"datetime":"2020-06-22T13:56:10.612Z","bid":0.18867,"ask":0.18871,"close":0.18869,"last":0.18869,"baseVolume":1645800,"quoteVolume":308083.475,"info":{"market":"XRPUSDT","period":"D1","timestamp":"2020-06-22T13:56:10.612Z","ask":"0.18871","bid":"0.18867","open":"0.18775","high":null,"low":null,"last":"0.18869","volume":"1645800","volumeQuote":"308083.475"}}]},"orderBook":{"statusCode":200,"response":{"bids":[],"asks":[],"timestamp":1592833904978,"datetime":"2020-06-22T13:51:44.978Z"}},"trades":{"statusCode":200,"response":[{"id":"1043212","info":{"id":1043212,"timestamp":"2020-04-01T14:40:23.136","direction":"BUY","price":"0.0005","quantity":"10000"},"timestamp":1585752023136,"datetime":"2020-04-01T14:40:23.136Z","symbol":"TPT/BTC","side":"buy","price":0.0005,"amount":10000}]}}